py_jsearch/__init__.py
py_jsearch/_types.py
py_jsearch/clients.py
py_jsearch/errors.py
py_jsearch/py.typed
py_jsearch-0.0.1.dist-info/METADATA
py_jsearch-0.0.1.dist-info/WHEEL
py_jsearch-0.0.1.dist-info/licenses/LICENSE
py_jsearch-0.0.1.dist-info/RECORD
