Metadata-Version: 2.4
Name: py-jsearch
Version: 0.0.1
Summary: Unofficial Python client for JSearch API by Open Web Ninja
Author-email: Taiwo-Sh <taiwo.r.shotunde@gmail.com>
License-File: LICENSE
Requires-Python: >=3.8
Requires-Dist: httpx>=0.28.1
Requires-Dist: pydantic
Requires-Dist: typing-extensions>=4.13.2
